[
  {
    "ja_transcribed": "[今宵|こ|よい]の[映画|えい|が]は「ツインズ」です。",
    "en": [
      "Tonight's movie will be \"Twins\"."
    ],
    "source": "tatoeba",
    "lesson": "L141",
    "transcription_author": "small_snow",
    "char_length": 15,
    "length_bucket": "medium",
    "required_words": 1,
    "kic_words_current_lesson": [
      {
        "word": "宵",
        "lesson": "L141",
        "kanji_ids": [
          "1907"
        ],
        "reading": "よい",
        "quiz": true
      }
    ],
    "kic_words_previous_lessons": [
      {
        "word": "映画",
        "lesson": "L011",
        "kanji_ids": [
          "0234",
          "0235"
        ],
        "reading": "えいが",
        "quiz": true
      },
      {
        "word": "今",
        "lesson": "L002",
        "kanji_ids": [
          "0027"
        ],
        "reading": "こ",
        "quiz": true
      }
    ],
    "non_kic_words": [],
    "target_kanji_ids": [
      "1907"
    ],
    "sentence_kanji_ids": [
      "0027",
      "0234",
      "0235",
      "1907"
    ],
    "id": "grade1:medium:L141:40de9a358e"
  },
  {
    "ja_transcribed": "[彼女|かの|じょ]は[琴|こと]を[弾|ひ]くことがとても[好|す]きだ。",
    "en": [
      "She likes to play the koto very much."
    ],
    "source": "tatoeba",
    "lesson": "L141",
    "transcription_author": "small_snow",
    "char_length": 17,
    "length_bucket": "medium",
    "required_words": 1,
    "kic_words_current_lesson": [
      {
        "word": "琴",
        "lesson": "L141",
        "kanji_ids": [
          "1906"
        ],
        "reading": "こと",
        "quiz": true
      }
    ],
    "kic_words_previous_lessons": [
      {
        "word": "弾く",
        "lesson": "L039",
        "kanji_ids": [
          "0590"
        ],
        "reading": "ひく",
        "quiz": true
      },
      {
        "word": "彼女",
        "lesson": "L090",
        "kanji_ids": [
          "1146"
        ],
        "reading": "かのじょ",
        "quiz": true
      }
    ],
    "non_kic_words": [
      {
        "surface": "好",
        "reading": "す",
        "kanji_ids": [
          "0244"
        ],
        "max_kic_lesson": "L011",
        "quiz": true
      }
    ],
    "target_kanji_ids": [
      "1906"
    ],
    "sentence_kanji_ids": [
      "0244",
      "0590",
      "1146",
      "1906"
    ],
    "id": "grade1:medium:L141:234fa72267"
  },
  {
    "ja_transcribed": "[観客|かん|きゃく]はコンサートの[余韻|よ|いん]に[浸|ひた]っていた。",
    "en": [
      "The audience was immersed in an aftertaste of the concert."
    ],
    "source": "tatoeba",
    "lesson": "L141",
    "transcription_author": "small_snow",
    "char_length": 18,
    "length_bucket": "medium",
    "required_words": 1,
    "kic_words_current_lesson": [
      {
        "word": "韻",
        "lesson": "L141",
        "kanji_ids": [
          "1903"
        ],
        "reading": "いん",
        "quiz": true
      }
    ],
    "kic_words_previous_lessons": [
      {
        "word": "観客",
        "lesson": "L059",
        "kanji_ids": [
          "0805"
        ],
        "reading": "かんきゃく",
        "quiz": true
      }
    ],
    "non_kic_words": [
      {
        "surface": "浸",
        "reading": "ひた",
        "kanji_ids": [],
        "max_kic_lesson": "L120",
        "quiz": true
      }
    ],
    "target_kanji_ids": [
      "1903"
    ],
    "sentence_kanji_ids": [
      "0805",
      "1903"
    ],
    "id": "grade1:medium:L141:01c7cfe1ef"
  },
  {
    "ja_transcribed": "メアリーはその[劇|げき]で[老婆|ろう|ば]の[役|やく]を[演|えん]じた。",
    "en": [
      "Mary played the role of an old woman in the play."
    ],
    "source": "tatoeba",
    "lesson": "L141",
    "transcription_author": "KK_kaku_",
    "char_length": 18,
    "length_bucket": "medium",
    "required_words": 1,
    "kic_words_current_lesson": [
      {
        "word": "老婆",
        "lesson": "L141",
        "kanji_ids": [
          "1902"
        ],
        "reading": "ろうば",
        "quiz": true
      }
    ],
    "kic_words_previous_lessons": [
      {
        "word": "役",
        "lesson": "L041",
        "kanji_ids": [
          "0609"
        ],
        "reading": "やく",
        "quiz": true
      },
      {
        "word": "劇",
        "lesson": "L089",
        "kanji_ids": [
          "1140"
        ],
        "reading": "げき",
        "quiz": true
      }
    ],
    "non_kic_words": [
      {
        "surface": "演",
        "reading": "えん",
        "kanji_ids": [
          "0616"
        ],
        "max_kic_lesson": "L041",
        "quiz": true
      }
    ],
    "target_kanji_ids": [
      "1902"
    ],
    "sentence_kanji_ids": [
      "0609",
      "0616",
      "1140",
      "1902"
    ],
    "id": "grade1:medium:L141:5cc5094d98"
  },
  {
    "ja_transcribed": "それは[大|おお]きくて[黒|くろ]いアメリカの[軍艦|ぐん|かん]だった。",
    "en": [
      "It was a big black American warship."
    ],
    "source": "tatoeba",
    "lesson": "L141",
    "transcription_author": "small_snow",
    "char_length": 20,
    "length_bucket": "medium",
    "required_words": 1,
    "kic_words_current_lesson": [
      {
        "word": "軍艦",
        "lesson": "L141",
        "kanji_ids": [
          "1892"
        ],
        "reading": "ぐんかん",
        "quiz": true
      }
    ],
    "kic_words_previous_lessons": [
      {
        "word": "黒い",
        "lesson": "L002",
        "kanji_ids": [
          "0045"
        ],
        "reading": "くろい",
        "quiz": true
      }
    ],
    "non_kic_words": [
      {
        "surface": "大",
        "reading": "おお",
        "kanji_ids": [
          "0087"
        ],
        "max_kic_lesson": null,
        "quiz": true
      }
    ],
    "target_kanji_ids": [
      "1892"
    ],
    "sentence_kanji_ids": [
      "0045",
      "0087",
      "1892"
    ],
    "id": "grade1:medium:L141:84c073f178"
  },
  {
    "ja_transcribed": "[１人|ひとり]の[老婆|ろう|ば]が[不自由|ふ|じ|ゆう]な[足|あし]で[通|とお]りを[歩|ある]いていた。",
    "en": [
      "An old woman limped along the street."
    ],
    "source": "tatoeba",
    "lesson": "L141",
    "transcription_author": "small_snow",
    "char_length": 21,
    "length_bucket": "medium",
    "required_words": 1,
    "kic_words_current_lesson": [
      {
        "word": "老婆",
        "lesson": "L141",
        "kanji_ids": [
          "1902"
        ],
        "reading": "ろうば",
        "quiz": true
      }
    ],
    "kic_words_previous_lessons": [
      {
        "word": "不自由な",
        "lesson": "L042",
        "kanji_ids": [
          "0623"
        ],
        "reading": "ふじゆうな",
        "quiz": true
      },
      {
        "word": "人",
        "lesson": "L001",
        "kanji_ids": [
          "0015"
        ],
        "reading": "人[ひと]",
        "quiz": false
      },
      {
        "word": "足",
        "lesson": "L007",
        "kanji_ids": [
          "0171"
        ],
        "reading": "あし",
        "quiz": true
      },
      {
        "word": "通",
        "lesson": "L009",
        "kanji_ids": [
          "0204"
        ],
        "reading": "とお",
        "quiz": true
      }
    ],
    "non_kic_words": [
      {
        "surface": "歩",
        "reading": "ある",
        "kanji_ids": [
          "0176"
        ],
        "max_kic_lesson": "L008",
        "quiz": true
      }
    ],
    "target_kanji_ids": [
      "1902"
    ],
    "sentence_kanji_ids": [
      "0015",
      "0171",
      "0176",
      "0204",
      "0623",
      "1902"
    ],
    "id": "grade1:medium:L141:1c55edfb40"
  },
  {
    "ja_transcribed": "[女王|じょ|おう]と[謁見|えっ|けん][出来|で|き]る[日|ひ]がくるなんて[夢|ゆめ]のようだ。",
    "en": [
      "It feels like a dream to be able to meet with the queen."
    ],
    "source": "tatoeba",
    "lesson": "L141",
    "transcription_author": "KK_kaku_",
    "char_length": 21,
    "length_bucket": "medium",
    "required_words": 1,
    "kic_words_current_lesson": [
      {
        "word": "謁見",
        "lesson": "L141",
        "kanji_ids": [
          "1899"
        ],
        "reading": "えっけん",
        "quiz": true
      }
    ],
    "kic_words_previous_lessons": [
      {
        "word": "来る",
        "lesson": "L006",
        "kanji_ids": [
          "0133"
        ],
        "reading": "きる",
        "quiz": true
      },
      {
        "word": "女王",
        "lesson": "L038",
        "kanji_ids": [
          "0577"
        ],
        "reading": "じょおう",
        "quiz": true
      },
      {
        "word": "日",
        "lesson": "L001",
        "kanji_ids": [
          "0016"
        ],
        "reading": "ひ",
        "quiz": true
      },
      {
        "word": "夢",
        "lesson": "L058",
        "kanji_ids": [
          "0800"
        ],
        "reading": "ゆめ",
        "quiz": true
      }
    ],
    "non_kic_words": [],
    "target_kanji_ids": [
      "1899"
    ],
    "sentence_kanji_ids": [
      "0016",
      "0133",
      "0577",
      "0800",
      "1899"
    ],
    "id": "grade1:medium:L141:9cec49f759"
  },
  {
    "ja_transcribed": "モノを[買|か]う[時|とき]は、よく[吟味|ぎん|み]してから[買|か]いなさい。",
    "en": [
      "When you buy something, examine it carefully before you buy it."
    ],
    "source": "tatoeba",
    "lesson": "L141",
    "transcription_author": "small_snow",
    "char_length": 22,
    "length_bucket": "medium",
    "required_words": 1,
    "kic_words_current_lesson": [
      {
        "word": "吟味",
        "lesson": "L141",
        "kanji_ids": [
          "1904"
        ],
        "reading": "ぎんみ",
        "quiz": true
      }
    ],
    "kic_words_previous_lessons": [
      {
        "word": "買う",
        "lesson": "L008",
        "kanji_ids": [
          "0188"
        ],
        "reading": "かう",
        "quiz": true
      },
      {
        "word": "時",
        "lesson": "L001",
        "kanji_ids": [
          "0025"
        ],
        "reading": "とき",
        "quiz": true
      }
    ],
    "non_kic_words": [
      {
        "surface": "買",
        "reading": "か",
        "kanji_ids": [
          "0188"
        ],
        "max_kic_lesson": "L008",
        "quiz": true
      }
    ],
    "target_kanji_ids": [
      "1904"
    ],
    "sentence_kanji_ids": [
      "0025",
      "0188",
      "1904"
    ],
    "id": "grade1:medium:L141:6cacb47874"
  },
  {
    "ja_transcribed": "みなさん、[今宵|こ|よい]はたくさん[飲|の]んで[食|た]べて[盛|も]り[上|あ]がりましょう！",
    "en": [
      "Everybody, let's eat and drink in plenty and have a great time tonight!"
    ],
    "source": "tatoeba",
    "lesson": "L141",
    "transcription_author": "small_snow",
    "char_length": 28,
    "length_bucket": "medium",
    "required_words": 1,
    "kic_words_current_lesson": [
      {
        "word": "宵",
        "lesson": "L141",
        "kanji_ids": [
          "1907"
        ],
        "reading": "よい",
        "quiz": true
      }
    ],
    "kic_words_previous_lessons": [
      {
        "word": "今",
        "lesson": "L002",
        "kanji_ids": [
          "0027"
        ],
        "reading": "こ",
        "quiz": true
      },
      {
        "word": "上",
        "lesson": "L002",
        "kanji_ids": [
          "0031"
        ],
        "reading": "あ",
        "quiz": true
      }
    ],
    "non_kic_words": [
      {
        "surface": "飲んで食べて盛",
        "reading": "のんでたべても",
        "kanji_ids": [
          "0131",
          "0132",
          "0922"
        ],
        "max_kic_lesson": "L069",
        "quiz": true
      }
    ],
    "target_kanji_ids": [
      "1907"
    ],
    "sentence_kanji_ids": [
      "0027",
      "0031",
      "0131",
      "0132",
      "0922",
      "1907"
    ],
    "id": "grade1:medium:L141:033937f5f3"
  }
]