[
  {
    "ja": "一般常識よ。",
    "en": [
      "It's common knowledge.",
      "It's common sense."
    ],
    "lesson": "L050",
    "required_words": 1,
    "char_length": 6,
    "length_bucket": "short",
    "kic_words_current_lesson": [
      {
        "word": "常識",
        "lesson": "L050",
        "kanji_ids": [
          "0512",
          "0708"
        ],
        "reading": "常[じょう]識[しき]"
      }
    ],
    "kic_words_previous_lessons": [],
    "target_kanji_ids": [
      "0512",
      "0708"
    ],
    "sentence_kanji_ids": [
      "0512",
      "0708"
    ],
    "id": "grade1:short:L050:84d2e62c13"
  },
  {
    "ja": "葉巻はいかが？",
    "en": [
      "Have a cigar?",
      "Would you like a cigar?"
    ],
    "lesson": "L050",
    "required_words": 1,
    "char_length": 7,
    "length_bucket": "short",
    "kic_words_current_lesson": [
      {
        "word": "葉巻",
        "lesson": "L050",
        "kanji_ids": [
          "0715"
        ],
        "reading": "葉[は]巻[まき]"
      }
    ],
    "kic_words_previous_lessons": [],
    "target_kanji_ids": [
      "0715"
    ],
    "sentence_kanji_ids": [
      "0715"
    ],
    "id": "grade1:short:L050:1be2914229"
  },
  {
    "ja": "回数券を下さい。",
    "en": [
      "May I have coupon tickets?"
    ],
    "lesson": "L050",
    "required_words": 1,
    "char_length": 8,
    "length_bucket": "short",
    "kic_words_current_lesson": [
      {
        "word": "回数券",
        "lesson": "L050",
        "kanji_ids": [
          "0714"
        ],
        "reading": "回[かい]数[すう]券[けん]"
      }
    ],
    "kic_words_previous_lessons": [
      {
        "word": "下",
        "lesson": "L002",
        "kanji_ids": [
          "0032"
        ],
        "reading": "下[した]"
      }
    ],
    "target_kanji_ids": [
      "0714"
    ],
    "sentence_kanji_ids": [
      "0032",
      "0714"
    ],
    "id": "grade1:short:L050:8f03a8b622"
  },
  {
    "ja": "そこの角ですよ。",
    "en": [
      "It's at the corner."
    ],
    "lesson": "L050",
    "required_words": 1,
    "char_length": 8,
    "length_bucket": "short",
    "kic_words_current_lesson": [
      {
        "word": "角",
        "lesson": "L050",
        "kanji_ids": [
          "0716"
        ],
        "reading": "角[かど]、角[つの]"
      }
    ],
    "kic_words_previous_lessons": [],
    "target_kanji_ids": [
      "0716"
    ],
    "sentence_kanji_ids": [
      "0716"
    ],
    "id": "grade1:short:L050:268a663bea"
  },
  {
    "ja": "角に置いといて。",
    "en": [
      "Put it in the corner."
    ],
    "lesson": "L050",
    "required_words": 1,
    "char_length": 8,
    "length_bucket": "short",
    "kic_words_current_lesson": [
      {
        "word": "角",
        "lesson": "L050",
        "kanji_ids": [
          "0716"
        ],
        "reading": "角[かど]、角[つの]"
      }
    ],
    "kic_words_previous_lessons": [],
    "target_kanji_ids": [
      "0716"
    ],
    "sentence_kanji_ids": [
      "0716"
    ],
    "id": "grade1:short:L050:b46821f2b9"
  },
  {
    "ja": "食堂はどこですか。",
    "en": [
      "Where is the cafeteria?",
      "Where's the cafeteria?"
    ],
    "lesson": "L050",
    "required_words": 1,
    "char_length": 9,
    "length_bucket": "short",
    "kic_words_current_lesson": [
      {
        "word": "食堂",
        "lesson": "L050",
        "kanji_ids": [
          "0709"
        ],
        "reading": "食[しょく]堂[どう]"
      }
    ],
    "kic_words_previous_lessons": [],
    "target_kanji_ids": [
      "0709"
    ],
    "sentence_kanji_ids": [
      "0709"
    ],
    "id": "grade1:short:L050:0a9fb524ff"
  },
  {
    "ja": "今日は非常に暑い。",
    "en": [
      "Today is extremely hot."
    ],
    "lesson": "L050",
    "required_words": 1,
    "char_length": 9,
    "length_bucket": "short",
    "kic_words_current_lesson": [
      {
        "word": "常に",
        "lesson": "L050",
        "kanji_ids": [
          "0708"
        ],
        "reading": "常[つね]に"
      }
    ],
    "kic_words_previous_lessons": [
      {
        "word": "今日",
        "lesson": "L001",
        "kanji_ids": [
          "0016",
          "0027"
        ],
        "reading": "今[こん]日[にち]、今日[きょう]"
      },
      {
        "word": "暑い",
        "lesson": "L005",
        "kanji_ids": [
          "0119"
        ],
        "reading": "暑[あつ]い"
      }
    ],
    "target_kanji_ids": [
      "0708"
    ],
    "sentence_kanji_ids": [
      "0016",
      "0027",
      "0119",
      "0708"
    ],
    "id": "grade1:short:L050:767987904d"
  },
  {
    "ja": "１等賞を取ったぞ。",
    "en": [
      "I've won first prize!",
      "I won first prize."
    ],
    "lesson": "L050",
    "required_words": 1,
    "char_length": 9,
    "length_bucket": "short",
    "kic_words_current_lesson": [
      {
        "word": "賞",
        "lesson": "L050",
        "kanji_ids": [
          "0711"
        ],
        "reading": "賞[しょう]"
      }
    ],
    "kic_words_previous_lessons": [],
    "target_kanji_ids": [
      "0711"
    ],
    "sentence_kanji_ids": [
      "0711"
    ],
    "id": "grade1:short:L050:72b0674dd1"
  },
  {
    "ja": "葉巻を吸いますか。",
    "en": [
      "Do you smoke cigars?"
    ],
    "lesson": "L050",
    "required_words": 1,
    "char_length": 9,
    "length_bucket": "short",
    "kic_words_current_lesson": [
      {
        "word": "葉巻",
        "lesson": "L050",
        "kanji_ids": [
          "0715"
        ],
        "reading": "葉[は]巻[まき]"
      }
    ],
    "kic_words_previous_lessons": [],
    "target_kanji_ids": [
      "0715"
    ],
    "sentence_kanji_ids": [
      "0715"
    ],
    "id": "grade1:short:L050:2585c0c08d"
  },
  {
    "ja": "そんなの常識だよ。",
    "en": [
      "That's common sense."
    ],
    "lesson": "L050",
    "required_words": 1,
    "char_length": 9,
    "length_bucket": "short",
    "kic_words_current_lesson": [
      {
        "word": "常識",
        "lesson": "L050",
        "kanji_ids": [
          "0512",
          "0708"
        ],
        "reading": "常[じょう]識[しき]"
      }
    ],
    "kic_words_previous_lessons": [],
    "target_kanji_ids": [
      "0512",
      "0708"
    ],
    "sentence_kanji_ids": [
      "0512",
      "0708"
    ],
    "id": "grade1:short:L050:fd4ba40dee"
  },
  {
    "ja": "非常に困っています。",
    "en": [
      "I am in deep water."
    ],
    "lesson": "L050",
    "required_words": 1,
    "char_length": 10,
    "length_bucket": "short",
    "kic_words_current_lesson": [
      {
        "word": "常に",
        "lesson": "L050",
        "kanji_ids": [
          "0708"
        ],
        "reading": "常[つね]に"
      }
    ],
    "kic_words_previous_lessons": [],
    "target_kanji_ids": [
      "0708"
    ],
    "sentence_kanji_ids": [
      "0708"
    ],
    "id": "grade1:short:L050:ad713efdbc"
  },
  {
    "ja": "直角は９０度である。",
    "en": [
      "A right angle has ninety degrees."
    ],
    "lesson": "L050",
    "required_words": 1,
    "char_length": 10,
    "length_bucket": "short",
    "kic_words_current_lesson": [
      {
        "word": "角",
        "lesson": "L050",
        "kanji_ids": [
          "0716"
        ],
        "reading": "角[かど]、角[つの]"
      }
    ],
    "kic_words_previous_lessons": [
      {
        "word": "度",
        "lesson": "L017",
        "kanji_ids": [
          "0333"
        ],
        "reading": "～度[ど]"
      }
    ],
    "target_kanji_ids": [
      "0716"
    ],
    "sentence_kanji_ids": [
      "0333",
      "0716"
    ],
    "id": "grade1:short:L050:9710fb56c4"
  },
  {
    "ja": "常に正しい事をせよ。",
    "en": [
      "Always do what is right."
    ],
    "lesson": "L050",
    "required_words": 1,
    "char_length": 10,
    "length_bucket": "short",
    "kic_words_current_lesson": [
      {
        "word": "常に",
        "lesson": "L050",
        "kanji_ids": [
          "0708"
        ],
        "reading": "常[つね]に"
      }
    ],
    "kic_words_previous_lessons": [
      {
        "word": "正しい",
        "lesson": "L024",
        "kanji_ids": [
          "0407"
        ],
        "reading": "正[ただ]しい"
      }
    ],
    "target_kanji_ids": [
      "0708"
    ],
    "sentence_kanji_ids": [
      "0407",
      "0708"
    ],
    "id": "grade1:short:L050:f39c51eae2"
  },
  {
    "ja": "今週は非常に忙しい。",
    "en": [
      "I'm very busy this week."
    ],
    "lesson": "L050",
    "required_words": 1,
    "char_length": 10,
    "length_bucket": "short",
    "kic_words_current_lesson": [
      {
        "word": "常に",
        "lesson": "L050",
        "kanji_ids": [
          "0708"
        ],
        "reading": "常[つね]に"
      }
    ],
    "kic_words_previous_lessons": [
      {
        "word": "忙しい",
        "lesson": "L005",
        "kanji_ids": [
          "0126"
        ],
        "reading": "忙[いそが]しい"
      },
      {
        "word": "今週",
        "lesson": "L002",
        "kanji_ids": [
          "0027",
          "0163"
        ],
        "reading": "今[こん]週[しゅう]"
      }
    ],
    "target_kanji_ids": [
      "0708"
    ],
    "sentence_kanji_ids": [
      "0027",
      "0126",
      "0163",
      "0708"
    ],
    "id": "grade1:short:L050:b6eed1dd9e"
  },
  {
    "ja": "学識と常識は別物だ。",
    "en": [
      "Learning is one thing, and common sense another."
    ],
    "lesson": "L050",
    "required_words": 1,
    "char_length": 10,
    "length_bucket": "short",
    "kic_words_current_lesson": [
      {
        "word": "常識",
        "lesson": "L050",
        "kanji_ids": [
          "0512",
          "0708"
        ],
        "reading": "常[じょう]識[しき]"
      }
    ],
    "kic_words_previous_lessons": [
      {
        "word": "物",
        "lesson": "L016",
        "kanji_ids": [
          "0321"
        ],
        "reading": "物[もの]"
      }
    ],
    "target_kanji_ids": [
      "0512",
      "0708"
    ],
    "sentence_kanji_ids": [
      "0321",
      "0512",
      "0708"
    ],
    "id": "grade1:short:L050:eff5f907ac"
  },
  {
    "ja": "悪い本は害を与える。",
    "en": [
      "Bad books will do you harm."
    ],
    "lesson": "L050",
    "required_words": 1,
    "char_length": 10,
    "length_bucket": "short",
    "kic_words_current_lesson": [
      {
        "word": "与える",
        "lesson": "L050",
        "kanji_ids": [
          "0713"
        ],
        "reading": "与[あた]える"
      }
    ],
    "kic_words_previous_lessons": [
      {
        "word": "悪い",
        "lesson": "L005",
        "kanji_ids": [
          "0114"
        ],
        "reading": "悪[わる]い"
      },
      {
        "word": "本",
        "lesson": "L002",
        "kanji_ids": [
          "0037"
        ],
        "reading": "本[ほん]、本[もと]"
      }
    ],
    "target_kanji_ids": [
      "0713"
    ],
    "sentence_kanji_ids": [
      "0037",
      "0114",
      "0713"
    ],
    "id": "grade1:short:L050:a5f92bf838"
  },
  {
    "ja": "ヘビがとぐろを巻く。",
    "en": [
      "The snake coils itself up."
    ],
    "lesson": "L050",
    "required_words": 1,
    "char_length": 10,
    "length_bucket": "short",
    "kic_words_current_lesson": [
      {
        "word": "巻く",
        "lesson": "L050",
        "kanji_ids": [
          "0715"
        ],
        "reading": "巻[ま]く"
      }
    ],
    "kic_words_previous_lessons": [],
    "target_kanji_ids": [
      "0715"
    ],
    "sentence_kanji_ids": [
      "0715"
    ],
    "id": "grade1:short:L050:3f9c995921"
  }
]