[
  {
    "ja": "武雄は受かり、邦夫は受からないと思っていたが、結果は逆だった。",
    "en": [
      "I thought that Takeo would pass the exam and Kunio would fail, but the result was the other way around."
    ],
    "lesson": "L127",
    "required_words": 1,
    "char_length": 31,
    "length_bucket": "long",
    "kic_words_current_lesson": [
      {
        "word": "雄",
        "lesson": "L127",
        "kanji_ids": [
          "1637"
        ],
        "reading": "雄[おす]"
      }
    ],
    "kic_words_previous_lessons": [
      {
        "word": "結果",
        "lesson": "L031",
        "kanji_ids": [
          "0502"
        ],
        "reading": "結[けっ]果[か]"
      },
      {
        "word": "夫",
        "lesson": "L040",
        "kanji_ids": [
          "0595"
        ],
        "reading": "夫[おっと]"
      }
    ],
    "target_kanji_ids": [
      "1637"
    ],
    "sentence_kanji_ids": [
      "0502",
      "0595",
      "1637"
    ],
    "id": "grade1:long:L127:155d8f8f73"
  },
  {
    "ja": "彼の雄弁は素晴らしいものだったので、誰もが感動して涙を流した。",
    "en": [
      "Such was his eloquence that everybody was moved to tears."
    ],
    "lesson": "L127",
    "required_words": 1,
    "char_length": 31,
    "length_bucket": "long",
    "kic_words_current_lesson": [
      {
        "word": "雄",
        "lesson": "L127",
        "kanji_ids": [
          "1637"
        ],
        "reading": "雄[おす]"
      }
    ],
    "kic_words_previous_lessons": [
      {
        "word": "素晴らしい",
        "lesson": "L043",
        "kanji_ids": [
          "0636"
        ],
        "reading": "素[す]晴[ば]らしい"
      },
      {
        "word": "誰",
        "lesson": "L004",
        "kanji_ids": [
          "0081"
        ],
        "reading": "誰[だれ]"
      },
      {
        "word": "涙",
        "lesson": "L084",
        "kanji_ids": [
          "1081"
        ],
        "reading": "涙[なみだ]"
      },
      {
        "word": "彼",
        "lesson": "L090",
        "kanji_ids": [
          "1146"
        ],
        "reading": "彼[かれ]"
      }
    ],
    "target_kanji_ids": [
      "1637"
    ],
    "sentence_kanji_ids": [
      "0081",
      "0636",
      "1081",
      "1146",
      "1637"
    ],
    "id": "grade1:long:L127:0ec91b74ad"
  },
  {
    "ja": "能力ということが社員を昇進させる際考慮される唯一の要素である。",
    "en": [
      "Ability is the only factor considered in promoting employees."
    ],
    "lesson": "L127",
    "required_words": 1,
    "char_length": 31,
    "length_bucket": "long",
    "kic_words_current_lesson": [
      {
        "word": "唯一の",
        "lesson": "L127",
        "kanji_ids": [
          "0001",
          "1636"
        ],
        "reading": "唯[ゆい]一[いつ]の"
      }
    ],
    "kic_words_previous_lessons": [
      {
        "word": "社員",
        "lesson": "L023",
        "kanji_ids": [
          "0060",
          "0395"
        ],
        "reading": "社[しゃ]員[いん]"
      },
      {
        "word": "能力",
        "lesson": "L024",
        "kanji_ids": [
          "0173",
          "0411"
        ],
        "reading": "能[のう]力[りょく]"
      },
      {
        "word": "昇進",
        "lesson": "L102",
        "kanji_ids": [
          "1280"
        ],
        "reading": "昇[しょう]進[しん]"
      },
      {
        "word": "考慮",
        "lesson": "L112",
        "kanji_ids": [
          "0212",
          "1377"
        ],
        "reading": "考[こう]慮[りょ]"
      },
      {
        "word": "要",
        "lesson": "L025",
        "kanji_ids": [
          "0424"
        ],
        "reading": "要[かなめ]"
      }
    ],
    "target_kanji_ids": [
      "0001",
      "1636"
    ],
    "sentence_kanji_ids": [
      "0001",
      "0060",
      "0173",
      "0212",
      "0395",
      "0411",
      "0424",
      "1280",
      "1377",
      "1636"
    ],
    "id": "grade1:long:L127:dc07610262"
  },
  {
    "ja": "合衆国では２億１６００万丁もの鉄砲類が、民間の手にあるという。",
    "en": [
      "In the U.S., as many as 216 million firearms are said to be in private hands."
    ],
    "lesson": "L127",
    "required_words": 1,
    "char_length": 31,
    "length_bucket": "long",
    "kic_words_current_lesson": [
      {
        "word": "鉄砲",
        "lesson": "L127",
        "kanji_ids": [
          "1631"
        ],
        "reading": "鉄[てっ]砲[ぽう]"
      }
    ],
    "kic_words_previous_lessons": [
      {
        "word": "民間の",
        "lesson": "L035",
        "kanji_ids": [
          "0536"
        ],
        "reading": "民[みん]間[かん]の"
      },
      {
        "word": "国",
        "lesson": "L006",
        "kanji_ids": [
          "0151"
        ],
        "reading": "国[くに]"
      },
      {
        "word": "手",
        "lesson": "L007",
        "kanji_ids": [
          "0170"
        ],
        "reading": "手[て]"
      },
      {
        "word": "億",
        "lesson": "L044",
        "kanji_ids": [
          "0650"
        ],
        "reading": "～億[おく]"
      }
    ],
    "target_kanji_ids": [
      "1631"
    ],
    "sentence_kanji_ids": [
      "0151",
      "0170",
      "0536",
      "0650",
      "1631"
    ],
    "id": "grade1:long:L127:612379d2cf"
  },
  {
    "ja": "ボブは私たちのクラスの中でスペイン語が話せる唯一の学生である。",
    "en": [
      "Bob is the only student that can speak Spanish in our class."
    ],
    "lesson": "L127",
    "required_words": 1,
    "char_length": 31,
    "length_bucket": "long",
    "kic_words_current_lesson": [
      {
        "word": "唯一の",
        "lesson": "L127",
        "kanji_ids": [
          "0001",
          "1636"
        ],
        "reading": "唯[ゆい]一[いつ]の"
      }
    ],
    "kic_words_previous_lessons": [
      {
        "word": "学生",
        "lesson": "L002",
        "kanji_ids": [
          "0049",
          "0050"
        ],
        "reading": "学[がく]生[せい]"
      },
      {
        "word": "中",
        "lesson": "L002",
        "kanji_ids": [
          "0033"
        ],
        "reading": "中[なか]"
      },
      {
        "word": "私",
        "lesson": "L003",
        "kanji_ids": [
          "0072"
        ],
        "reading": "私[わたし]、私[わたくし]"
      }
    ],
    "target_kanji_ids": [
      "0001",
      "1636"
    ],
    "sentence_kanji_ids": [
      "0001",
      "0033",
      "0049",
      "0050",
      "0072",
      "1636"
    ],
    "id": "grade1:long:L127:396d00884b"
  },
  {
    "ja": "その兵士たちは勇敢に戦ったが、結局降伏しなければならなかった。",
    "en": [
      "The soldiers fought valiantly, but finally they had to give in."
    ],
    "lesson": "L127",
    "required_words": 1,
    "char_length": 31,
    "length_bucket": "long",
    "kic_words_current_lesson": [
      {
        "word": "勇敢に",
        "lesson": "L127",
        "kanji_ids": [
          "1622"
        ],
        "reading": "勇[ゆう]敢[かん]に"
      }
    ],
    "kic_words_previous_lessons": [
      {
        "word": "結局",
        "lesson": "L011",
        "kanji_ids": [
          "0228"
        ],
        "reading": "結[けっ]局[きょく]"
      },
      {
        "word": "兵士",
        "lesson": "L076",
        "kanji_ids": [
          "0994"
        ],
        "reading": "兵[へい]士[し]"
      }
    ],
    "target_kanji_ids": [
      "1622"
    ],
    "sentence_kanji_ids": [
      "0228",
      "0994",
      "1622"
    ],
    "id": "grade1:long:L127:bcbc9b40c0"
  },
  {
    "ja": "世界中の数百万の子供にとって、学校給食はその日唯一の食事です。",
    "en": [
      "For millions of children around the world, the meal they get at school is the only meal they get in a day."
    ],
    "lesson": "L127",
    "required_words": 1,
    "char_length": 31,
    "length_bucket": "long",
    "kic_words_current_lesson": [
      {
        "word": "唯一の",
        "lesson": "L127",
        "kanji_ids": [
          "0001",
          "1636"
        ],
        "reading": "唯[ゆい]一[いつ]の"
      }
    ],
    "kic_words_previous_lessons": [
      {
        "word": "世界中",
        "lesson": "L002",
        "kanji_ids": [
          "0033"
        ],
        "reading": "世[せ]界[かい]中[じゅう]"
      },
      {
        "word": "学校",
        "lesson": "L002",
        "kanji_ids": [
          "0050",
          "0051"
        ],
        "reading": "学[がっ]校[こう]"
      },
      {
        "word": "食事",
        "lesson": "L006",
        "kanji_ids": [
          "0131"
        ],
        "reading": "食[しょく]事[じ]"
      },
      {
        "word": "子供",
        "lesson": "L025",
        "kanji_ids": [
          "0418"
        ],
        "reading": "子[こ]供[ども]"
      },
      {
        "word": "百",
        "lesson": "L001",
        "kanji_ids": [
          "0011"
        ],
        "reading": "百[ひゃく]"
      },
      {
        "word": "日",
        "lesson": "L001",
        "kanji_ids": [
          "0016"
        ],
        "reading": "日[ひ]"
      },
      {
        "word": "数",
        "lesson": "L034",
        "kanji_ids": [
          "0529"
        ],
        "reading": "数[かず]"
      }
    ],
    "target_kanji_ids": [
      "0001",
      "1636"
    ],
    "sentence_kanji_ids": [
      "0001",
      "0011",
      "0016",
      "0033",
      "0050",
      "0051",
      "0131",
      "0418",
      "0529",
      "1636"
    ],
    "id": "grade1:long:L127:0b4a39624b"
  },
  {
    "ja": "わかった。わかった。わかったから、もう殴るのだけはやめてくれ。",
    "en": [
      "I know. I know. I get it already, so stop hitting me."
    ],
    "lesson": "L127",
    "required_words": 1,
    "char_length": 31,
    "length_bucket": "long",
    "kic_words_current_lesson": [
      {
        "word": "殴る",
        "lesson": "L127",
        "kanji_ids": [
          "1625"
        ],
        "reading": "殴[なぐ]る"
      }
    ],
    "kic_words_previous_lessons": [],
    "target_kanji_ids": [
      "1625"
    ],
    "sentence_kanji_ids": [
      "1625"
    ],
    "id": "grade1:long:L127:d859269470"
  },
  {
    "ja": "真理の発見はいつまでたっても科学の唯一の目的であらねばならない。",
    "en": [
      "The discovery of truth should remain the single aim of science."
    ],
    "lesson": "L127",
    "required_words": 1,
    "char_length": 32,
    "length_bucket": "long",
    "kic_words_current_lesson": [
      {
        "word": "唯一の",
        "lesson": "L127",
        "kanji_ids": [
          "0001",
          "1636"
        ],
        "reading": "唯[ゆい]一[いつ]の"
      }
    ],
    "kic_words_previous_lessons": [
      {
        "word": "真理",
        "lesson": "L011",
        "kanji_ids": [
          "0242"
        ],
        "reading": "真[しん]理[り]"
      },
      {
        "word": "発見",
        "lesson": "L014",
        "kanji_ids": [
          "0286"
        ],
        "reading": "発[はっ]見[けん]"
      },
      {
        "word": "目的",
        "lesson": "L021",
        "kanji_ids": [
          "0168",
          "0380"
        ],
        "reading": "目[もく]的[てき]"
      },
      {
        "word": "科学",
        "lesson": "L037",
        "kanji_ids": [
          "0565"
        ],
        "reading": "科[か]学[がく]"
      }
    ],
    "target_kanji_ids": [
      "0001",
      "1636"
    ],
    "sentence_kanji_ids": [
      "0001",
      "0168",
      "0242",
      "0286",
      "0380",
      "0565",
      "1636"
    ],
    "id": "grade1:long:L127:c9cc91a2d6"
  },
  {
    "ja": "かのローマの偉大な英雄、ジュリアス・シーザーは暗殺されたのです。",
    "en": [
      "The great Roman hero, Julius Caesar, was assassinated."
    ],
    "lesson": "L127",
    "required_words": 1,
    "char_length": 32,
    "length_bucket": "long",
    "kic_words_current_lesson": [
      {
        "word": "英雄",
        "lesson": "L127",
        "kanji_ids": [
          "1637"
        ],
        "reading": "英[えい]雄[ゆう]"
      }
    ],
    "kic_words_previous_lessons": [
      {
        "word": "偉大な",
        "lesson": "L099",
        "kanji_ids": [
          "1242"
        ],
        "reading": "偉[い]大[だい]な"
      },
      {
        "word": "暗殺",
        "lesson": "L041",
        "kanji_ids": [
          "0610"
        ],
        "reading": "暗[あん]殺[さつ]"
      }
    ],
    "target_kanji_ids": [
      "1637"
    ],
    "sentence_kanji_ids": [
      "0610",
      "1242",
      "1637"
    ],
    "id": "grade1:long:L127:56fc483169"
  },
  {
    "ja": "バス停に併設された団地で唯一のスーパー。歩いて数分の場所にある。",
    "en": [
      "There's a single supermarket in the apartment complex which adjoins the bus stop, a few minutes' walk away."
    ],
    "lesson": "L127",
    "required_words": 1,
    "char_length": 32,
    "length_bucket": "long",
    "kic_words_current_lesson": [
      {
        "word": "唯一の",
        "lesson": "L127",
        "kanji_ids": [
          "0001",
          "1636"
        ],
        "reading": "唯[ゆい]一[いつ]の"
      }
    ],
    "kic_words_previous_lessons": [
      {
        "word": "バス停",
        "lesson": "L030",
        "kanji_ids": [
          "0481"
        ],
        "reading": "バス停[てい]"
      },
      {
        "word": "場所",
        "lesson": "L017",
        "kanji_ids": [
          "0149",
          "0335"
        ],
        "reading": "場[ば]所[しょ]"
      },
      {
        "word": "分",
        "lesson": "L001",
        "kanji_ids": [
          "0026"
        ],
        "reading": "～分[ふん]、～分[ぷん]"
      },
      {
        "word": "数",
        "lesson": "L034",
        "kanji_ids": [
          "0529"
        ],
        "reading": "数[かず]"
      }
    ],
    "target_kanji_ids": [
      "0001",
      "1636"
    ],
    "sentence_kanji_ids": [
      "0001",
      "0026",
      "0149",
      "0335",
      "0481",
      "0529",
      "1636"
    ],
    "id": "grade1:long:L127:7d186ff8e6"
  },
  {
    "ja": "彼が鉄砲を掃除していたら暴発し、もう少しで妻に当たるところだった。",
    "en": [
      "The gun went off while he was cleaning it, and the bullet almost struck his wife."
    ],
    "lesson": "L127",
    "required_words": 1,
    "char_length": 33,
    "length_bucket": "long",
    "kic_words_current_lesson": [
      {
        "word": "鉄砲",
        "lesson": "L127",
        "kanji_ids": [
          "1631"
        ],
        "reading": "鉄[てっ]砲[ぽう]"
      }
    ],
    "kic_words_previous_lessons": [
      {
        "word": "当たる",
        "lesson": "L023",
        "kanji_ids": [
          "0402"
        ],
        "reading": "当[あ]たる"
      },
      {
        "word": "少し",
        "lesson": "L005",
        "kanji_ids": [
          "0105"
        ],
        "reading": "少[すこ]し"
      },
      {
        "word": "掃除",
        "lesson": "L072",
        "kanji_ids": [
          "0957",
          "0958"
        ],
        "reading": "掃[そう]除[じ]"
      },
      {
        "word": "発",
        "lesson": "L014",
        "kanji_ids": [
          "0286"
        ],
        "reading": "～発[はつ]"
      },
      {
        "word": "妻",
        "lesson": "L040",
        "kanji_ids": [
          "0596"
        ],
        "reading": "妻[つま]"
      },
      {
        "word": "彼",
        "lesson": "L090",
        "kanji_ids": [
          "1146"
        ],
        "reading": "彼[かれ]"
      }
    ],
    "target_kanji_ids": [
      "1631"
    ],
    "sentence_kanji_ids": [
      "0105",
      "0286",
      "0402",
      "0596",
      "0957",
      "0958",
      "1146",
      "1631"
    ],
    "id": "grade1:long:L127:cbc4c860d6"
  },
  {
    "ja": "かの偉大なローマの英雄、ジュリアス・シーザーは暗殺されたのだった。",
    "en": [
      "The great Roman hero, Julius Caesar, was assassinated."
    ],
    "lesson": "L127",
    "required_words": 1,
    "char_length": 33,
    "length_bucket": "long",
    "kic_words_current_lesson": [
      {
        "word": "英雄",
        "lesson": "L127",
        "kanji_ids": [
          "1637"
        ],
        "reading": "英[えい]雄[ゆう]"
      }
    ],
    "kic_words_previous_lessons": [
      {
        "word": "偉大な",
        "lesson": "L099",
        "kanji_ids": [
          "1242"
        ],
        "reading": "偉[い]大[だい]な"
      },
      {
        "word": "暗殺",
        "lesson": "L041",
        "kanji_ids": [
          "0610"
        ],
        "reading": "暗[あん]殺[さつ]"
      }
    ],
    "target_kanji_ids": [
      "1637"
    ],
    "sentence_kanji_ids": [
      "0610",
      "1242",
      "1637"
    ],
    "id": "grade1:long:L127:2f80820e93"
  },
  {
    "ja": "私をだますのも一度なら許す。だが、二度私をだましたら君は詐欺師だぞ。",
    "en": [
      "Deceive me once, and I will forgive you; deceive me twice, and you're a double-crosser."
    ],
    "lesson": "L127",
    "required_words": 1,
    "char_length": 34,
    "length_bucket": "long",
    "kic_words_current_lesson": [
      {
        "word": "詐欺",
        "lesson": "L127",
        "kanji_ids": [
          "1575",
          "1623"
        ],
        "reading": "詐[さ]欺[ぎ]"
      }
    ],
    "kic_words_previous_lessons": [
      {
        "word": "許す",
        "lesson": "L046",
        "kanji_ids": [
          "0667"
        ],
        "reading": "許[ゆる]す"
      },
      {
        "word": "私",
        "lesson": "L003",
        "kanji_ids": [
          "0072"
        ],
        "reading": "私[わたし]、私[わたくし]"
      },
      {
        "word": "度",
        "lesson": "L017",
        "kanji_ids": [
          "0333"
        ],
        "reading": "～度[ど]"
      },
      {
        "word": "君",
        "lesson": "L103",
        "kanji_ids": [
          "1289"
        ],
        "reading": "君[きみ]"
      }
    ],
    "target_kanji_ids": [
      "1575",
      "1623"
    ],
    "sentence_kanji_ids": [
      "0072",
      "0333",
      "0667",
      "1289",
      "1575",
      "1623"
    ],
    "id": "grade1:long:L127:9017434938"
  },
  {
    "ja": "詐欺、横領などの犯罪によりアメリカ人は以前より政府を信じなくなった。",
    "en": [
      "White collar crime has made American people trust the government less."
    ],
    "lesson": "L127",
    "required_words": 1,
    "char_length": 34,
    "length_bucket": "long",
    "kic_words_current_lesson": [
      {
        "word": "詐欺",
        "lesson": "L127",
        "kanji_ids": [
          "1575",
          "1623"
        ],
        "reading": "詐[さ]欺[ぎ]"
      }
    ],
    "kic_words_previous_lessons": [
      {
        "word": "アメリカ人",
        "lesson": "L001",
        "kanji_ids": [
          "0015"
        ],
        "reading": "アメリカ人[じん]"
      },
      {
        "word": "以前",
        "lesson": "L025",
        "kanji_ids": [
          "0420"
        ],
        "reading": "以[い]前[ぜん]"
      },
      {
        "word": "政府",
        "lesson": "L034",
        "kanji_ids": [
          "0530"
        ],
        "reading": "政[せい]府[ふ]"
      },
      {
        "word": "犯罪",
        "lesson": "L081",
        "kanji_ids": [
          "1046",
          "1047"
        ],
        "reading": "犯[はん]罪[ざい]"
      },
      {
        "word": "横",
        "lesson": "L002",
        "kanji_ids": [
          "0034"
        ],
        "reading": "横[よこ]"
      }
    ],
    "target_kanji_ids": [
      "1575",
      "1623"
    ],
    "sentence_kanji_ids": [
      "0015",
      "0034",
      "0420",
      "0530",
      "1046",
      "1047",
      "1575",
      "1623"
    ],
    "id": "grade1:long:L127:773aec96db"
  },
  {
    "ja": "あなたの菜園で作れる穀物や野菜を食べて生活する方がずっと安上がりだ。",
    "en": [
      "It's much cheaper to live on grains and vegetables you can grow in your garden."
    ],
    "lesson": "L127",
    "required_words": 1,
    "char_length": 34,
    "length_bucket": "long",
    "kic_words_current_lesson": [
      {
        "word": "穀物",
        "lesson": "L127",
        "kanji_ids": [
          "1627"
        ],
        "reading": "穀[こく]物[もつ]"
      }
    ],
    "kic_words_previous_lessons": [
      {
        "word": "生活",
        "lesson": "L033",
        "kanji_ids": [
          "0049",
          "0517"
        ],
        "reading": "生[せい]活[かつ]"
      },
      {
        "word": "野菜",
        "lesson": "L056",
        "kanji_ids": [
          "0404",
          "0774"
        ],
        "reading": "野[や]菜[さい]"
      },
      {
        "word": "菜園",
        "lesson": "L056",
        "kanji_ids": [
          "0774"
        ],
        "reading": "菜[さい]園[えん]"
      },
      {
        "word": "上",
        "lesson": "L002",
        "kanji_ids": [
          "0031"
        ],
        "reading": "上[うえ]"
      },
      {
        "word": "方",
        "lesson": "L002",
        "kanji_ids": [
          "0043"
        ],
        "reading": "方[ほう]"
      }
    ],
    "target_kanji_ids": [
      "1627"
    ],
    "sentence_kanji_ids": [
      "0031",
      "0043",
      "0049",
      "0404",
      "0517",
      "0774",
      "1627"
    ],
    "id": "grade1:long:L127:186b738352"
  }
]