[
  {
    "ja": "侮辱されたと感じて彼は怒った。",
    "en": [
      "Feeling himself insulted, he got angry."
    ],
    "lesson": "L136",
    "required_words": 1,
    "char_length": 15,
    "length_bucket": "medium",
    "kic_words_current_lesson": [
      {
        "word": "侮辱",
        "lesson": "L136",
        "kanji_ids": [
          "1795",
          "1801"
        ]
      }
    ],
    "kic_words_previous_lessons": [
      {
        "word": "彼",
        "lesson": "L090",
        "kanji_ids": [
          "1146"
        ]
      }
    ],
    "target_kanji_ids": [
      "1795",
      "1801"
    ],
    "sentence_kanji_ids": [
      "1146",
      "1795",
      "1801"
    ],
    "id": "grade2:medium:L136:ec2e47d7df"
  },
  {
    "ja": "彼女は幽霊を見てびっくりした。",
    "en": [
      "She was amazed at the sight of the ghost.",
      "She was surprised when she saw the ghost."
    ],
    "lesson": "L136",
    "required_words": 1,
    "char_length": 15,
    "length_bucket": "medium",
    "kic_words_current_lesson": [
      {
        "word": "幽霊",
        "lesson": "L136",
        "kanji_ids": [
          "1688",
          "1820"
        ]
      }
    ],
    "kic_words_previous_lessons": [
      {
        "word": "彼女",
        "lesson": "L090",
        "kanji_ids": [
          "1146"
        ]
      }
    ],
    "target_kanji_ids": [
      "1688",
      "1820"
    ],
    "sentence_kanji_ids": [
      "1146",
      "1688",
      "1820"
    ],
    "id": "grade2:medium:L136:7342bc1577"
  },
  {
    "ja": "彼女は自分の肖像画を描かせた。",
    "en": [
      "She sat for her portrait."
    ],
    "lesson": "L136",
    "required_words": 1,
    "char_length": 15,
    "length_bucket": "medium",
    "kic_words_current_lesson": [
      {
        "word": "肖像画",
        "lesson": "L136",
        "kanji_ids": [
          "1811"
        ]
      }
    ],
    "kic_words_previous_lessons": [
      {
        "word": "自分",
        "lesson": "L003",
        "kanji_ids": [
          "0063"
        ]
      },
      {
        "word": "彼女",
        "lesson": "L090",
        "kanji_ids": [
          "1146"
        ]
      }
    ],
    "target_kanji_ids": [
      "1811"
    ],
    "sentence_kanji_ids": [
      "0063",
      "1146",
      "1811"
    ],
    "id": "grade2:medium:L136:58c339b308"
  },
  {
    "ja": "彼女の私生活を知って幻滅した。",
    "en": [
      "I was disillusioned at her private life."
    ],
    "lesson": "L136",
    "required_words": 1,
    "char_length": 15,
    "length_bucket": "medium",
    "kic_words_current_lesson": [
      {
        "word": "幻滅",
        "lesson": "L136",
        "kanji_ids": [
          "1500",
          "1814"
        ]
      }
    ],
    "kic_words_previous_lessons": [
      {
        "word": "生活",
        "lesson": "L033",
        "kanji_ids": [
          "0049",
          "0517"
        ]
      },
      {
        "word": "彼女",
        "lesson": "L090",
        "kanji_ids": [
          "1146"
        ]
      },
      {
        "word": "私",
        "lesson": "L003",
        "kanji_ids": [
          "0072"
        ]
      }
    ],
    "target_kanji_ids": [
      "1500",
      "1814"
    ],
    "sentence_kanji_ids": [
      "0049",
      "0072",
      "0517",
      "1146",
      "1500",
      "1814"
    ],
    "id": "grade2:medium:L136:c9d8e33713"
  },
  {
    "ja": "彼は理由もなしに私を侮辱した。",
    "en": [
      "He insulted me without reason."
    ],
    "lesson": "L136",
    "required_words": 1,
    "char_length": 15,
    "length_bucket": "medium",
    "kic_words_current_lesson": [
      {
        "word": "侮辱",
        "lesson": "L136",
        "kanji_ids": [
          "1795",
          "1801"
        ]
      }
    ],
    "kic_words_previous_lessons": [
      {
        "word": "理由",
        "lesson": "L042",
        "kanji_ids": [
          "0623"
        ]
      },
      {
        "word": "私",
        "lesson": "L003",
        "kanji_ids": [
          "0072"
        ]
      },
      {
        "word": "彼",
        "lesson": "L090",
        "kanji_ids": [
          "1146"
        ]
      }
    ],
    "target_kanji_ids": [
      "1795",
      "1801"
    ],
    "sentence_kanji_ids": [
      "0072",
      "0623",
      "1146",
      "1795",
      "1801"
    ],
    "id": "grade2:medium:L136:658e73cb68"
  },
  {
    "ja": "彼は私をロバと呼んで侮辱した。",
    "en": [
      "He insulted me by calling me a donkey."
    ],
    "lesson": "L136",
    "required_words": 1,
    "char_length": 15,
    "length_bucket": "medium",
    "kic_words_current_lesson": [
      {
        "word": "侮辱",
        "lesson": "L136",
        "kanji_ids": [
          "1795",
          "1801"
        ]
      }
    ],
    "kic_words_previous_lessons": [
      {
        "word": "私",
        "lesson": "L003",
        "kanji_ids": [
          "0072"
        ]
      },
      {
        "word": "彼",
        "lesson": "L090",
        "kanji_ids": [
          "1146"
        ]
      }
    ],
    "target_kanji_ids": [
      "1795",
      "1801"
    ],
    "sentence_kanji_ids": [
      "0072",
      "1146",
      "1795",
      "1801"
    ],
    "id": "grade2:medium:L136:311f431ed7"
  },
  {
    "ja": "肺炎にかかると呼吸困難になる。",
    "en": [
      "Pneumonia causes difficulty in breathing."
    ],
    "lesson": "L136",
    "required_words": 1,
    "char_length": 15,
    "length_bucket": "medium",
    "kic_words_current_lesson": [
      {
        "word": "炎",
        "lesson": "L136",
        "kanji_ids": [
          "1803"
        ]
      }
    ],
    "kic_words_previous_lessons": [
      {
        "word": "呼吸",
        "lesson": "L013",
        "kanji_ids": [
          "0197",
          "0272"
        ]
      },
      {
        "word": "肺",
        "lesson": "L109",
        "kanji_ids": [
          "1343"
        ]
      }
    ],
    "target_kanji_ids": [
      "1803"
    ],
    "sentence_kanji_ids": [
      "0197",
      "0272",
      "1343",
      "1803"
    ],
    "id": "grade2:medium:L136:94871a064c"
  },
  {
    "ja": "二大文明はゆっくりと衰退した。",
    "en": [
      "Two great civilizations slowly fell into decay."
    ],
    "lesson": "L136",
    "required_words": 1,
    "char_length": 15,
    "length_bucket": "medium",
    "kic_words_current_lesson": [
      {
        "word": "衰退",
        "lesson": "L136",
        "kanji_ids": [
          "1805"
        ]
      }
    ],
    "kic_words_previous_lessons": [
      {
        "word": "文明",
        "lesson": "L016",
        "kanji_ids": [
          "0320"
        ]
      }
    ],
    "target_kanji_ids": [
      "1805"
    ],
    "sentence_kanji_ids": [
      "0320",
      "1805"
    ],
    "id": "grade2:medium:L136:244c4b1027"
  },
  {
    "ja": "暖炉の上に時計が掛かっている。",
    "en": [
      "The clock is above the fireplace."
    ],
    "lesson": "L136",
    "required_words": 1,
    "char_length": 15,
    "length_bucket": "medium",
    "kic_words_current_lesson": [
      {
        "word": "暖炉",
        "lesson": "L136",
        "kanji_ids": [
          "1802"
        ]
      }
    ],
    "kic_words_previous_lessons": [
      {
        "word": "時",
        "lesson": "L001",
        "kanji_ids": [
          "0025"
        ]
      },
      {
        "word": "上",
        "lesson": "L002",
        "kanji_ids": [
          "0031"
        ]
      }
    ],
    "target_kanji_ids": [
      "1802"
    ],
    "sentence_kanji_ids": [
      "0025",
      "0031",
      "1802"
    ],
    "id": "grade2:medium:L136:e976c8d9b0"
  },
  {
    "ja": "妻は今、肺炎にかかっています。",
    "en": [
      "My wife is suffering from pneumonia."
    ],
    "lesson": "L136",
    "required_words": 1,
    "char_length": 15,
    "length_bucket": "medium",
    "kic_words_current_lesson": [
      {
        "word": "炎",
        "lesson": "L136",
        "kanji_ids": [
          "1803"
        ]
      }
    ],
    "kic_words_previous_lessons": [
      {
        "word": "今",
        "lesson": "L002",
        "kanji_ids": [
          "0027"
        ]
      },
      {
        "word": "妻",
        "lesson": "L040",
        "kanji_ids": [
          "0596"
        ]
      },
      {
        "word": "肺",
        "lesson": "L109",
        "kanji_ids": [
          "1343"
        ]
      }
    ],
    "target_kanji_ids": [
      "1803"
    ],
    "sentence_kanji_ids": [
      "0027",
      "0596",
      "1343",
      "1803"
    ],
    "id": "grade2:medium:L136:34ea85ba68"
  },
  {
    "ja": "去年、中耳炎をわずらいました。",
    "en": [
      "I had otitis media last year.",
      "Last year I suffered from an inflammation of my middle ear."
    ],
    "lesson": "L136",
    "required_words": 1,
    "char_length": 15,
    "length_bucket": "medium",
    "kic_words_current_lesson": [
      {
        "word": "炎",
        "lesson": "L136",
        "kanji_ids": [
          "1803"
        ]
      }
    ],
    "kic_words_previous_lessons": [
      {
        "word": "去年",
        "lesson": "L001",
        "kanji_ids": [
          "0024",
          "0309"
        ]
      },
      {
        "word": "中",
        "lesson": "L002",
        "kanji_ids": [
          "0033"
        ]
      },
      {
        "word": "耳",
        "lesson": "L007",
        "kanji_ids": [
          "0169"
        ]
      }
    ],
    "target_kanji_ids": [
      "1803"
    ],
    "sentence_kanji_ids": [
      "0024",
      "0033",
      "0169",
      "0309",
      "1803"
    ],
    "id": "grade2:medium:L136:90fe721ac0"
  },
  {
    "ja": "火山が炎と煙を噴き出している。",
    "en": [
      "The volcano is belching out flames and smoke."
    ],
    "lesson": "L136",
    "required_words": 1,
    "char_length": 15,
    "length_bucket": "medium",
    "kic_words_current_lesson": [
      {
        "word": "炎",
        "lesson": "L136",
        "kanji_ids": [
          "1803"
        ]
      }
    ],
    "kic_words_previous_lessons": [
      {
        "word": "火山",
        "lesson": "L004",
        "kanji_ids": [
          "0100"
        ]
      },
      {
        "word": "煙",
        "lesson": "L080",
        "kanji_ids": [
          "1045"
        ]
      }
    ],
    "target_kanji_ids": [
      "1803"
    ],
    "sentence_kanji_ids": [
      "0100",
      "1045",
      "1803"
    ],
    "id": "grade2:medium:L136:9f829bbcd9"
  },
  {
    "ja": "じきにその衰弱は回復しますよ。",
    "en": [
      "You will recover from your weakness soon."
    ],
    "lesson": "L136",
    "required_words": 1,
    "char_length": 15,
    "length_bucket": "medium",
    "kic_words_current_lesson": [
      {
        "word": "衰弱",
        "lesson": "L136",
        "kanji_ids": [
          "1805"
        ]
      }
    ],
    "kic_words_previous_lessons": [
      {
        "word": "回復",
        "lesson": "L033",
        "kanji_ids": [
          "0521"
        ]
      }
    ],
    "target_kanji_ids": [
      "1805"
    ],
    "sentence_kanji_ids": [
      "0521",
      "1805"
    ],
    "id": "grade2:medium:L136:156e65e6a3"
  },
  {
    "ja": "あらゆる侮辱が彼に加えられた。",
    "en": [
      "Every insult was thrown at him."
    ],
    "lesson": "L136",
    "required_words": 1,
    "char_length": 15,
    "length_bucket": "medium",
    "kic_words_current_lesson": [
      {
        "word": "侮辱",
        "lesson": "L136",
        "kanji_ids": [
          "1795",
          "1801"
        ]
      }
    ],
    "kic_words_previous_lessons": [
      {
        "word": "彼",
        "lesson": "L090",
        "kanji_ids": [
          "1146"
        ]
      }
    ],
    "target_kanji_ids": [
      "1795",
      "1801"
    ],
    "sentence_kanji_ids": [
      "1146",
      "1795",
      "1801"
    ],
    "id": "grade2:medium:L136:445721029d"
  },
  {
    "ja": "いいえ、幽霊なんて怖くはない。",
    "en": [
      "No, I'm not afraid of ghosts."
    ],
    "lesson": "L136",
    "required_words": 1,
    "char_length": 15,
    "length_bucket": "medium",
    "kic_words_current_lesson": [
      {
        "word": "幽霊",
        "lesson": "L136",
        "kanji_ids": [
          "1688",
          "1820"
        ]
      }
    ],
    "kic_words_previous_lessons": [],
    "target_kanji_ids": [
      "1688",
      "1820"
    ],
    "sentence_kanji_ids": [
      "1688",
      "1820"
    ],
    "id": "grade2:medium:L136:452f1724b5"
  },
  {
    "ja": "彼は公衆の面前で私を侮辱した。",
    "en": [
      "He insulted me in public."
    ],
    "lesson": "L136",
    "required_words": 1,
    "char_length": 15,
    "length_bucket": "medium",
    "kic_words_current_lesson": [
      {
        "word": "侮辱",
        "lesson": "L136",
        "kanji_ids": [
          "1795",
          "1801"
        ]
      }
    ],
    "kic_words_previous_lessons": [
      {
        "word": "前",
        "lesson": "L002",
        "kanji_ids": [
          "0029"
        ]
      },
      {
        "word": "私",
        "lesson": "L003",
        "kanji_ids": [
          "0072"
        ]
      },
      {
        "word": "面",
        "lesson": "L026",
        "kanji_ids": [
          "0438"
        ]
      },
      {
        "word": "彼",
        "lesson": "L090",
        "kanji_ids": [
          "1146"
        ]
      }
    ],
    "target_kanji_ids": [
      "1795",
      "1801"
    ],
    "sentence_kanji_ids": [
      "0029",
      "0072",
      "0438",
      "1146",
      "1795",
      "1801"
    ],
    "id": "grade2:medium:L136:1dd5bade00"
  },
  {
    "ja": "トムは幽霊の存在を信じている。",
    "en": [
      "Tom believes in the existence of ghosts.",
      "Tom believes that ghosts exist.",
      "Tom believes ghosts exist."
    ],
    "lesson": "L136",
    "required_words": 1,
    "char_length": 15,
    "length_bucket": "medium",
    "kic_words_current_lesson": [
      {
        "word": "幽霊",
        "lesson": "L136",
        "kanji_ids": [
          "1688",
          "1820"
        ]
      }
    ],
    "kic_words_previous_lessons": [
      {
        "word": "存在",
        "lesson": "L039",
        "kanji_ids": [
          "0587",
          "0588"
        ]
      }
    ],
    "target_kanji_ids": [
      "1688",
      "1820"
    ],
    "sentence_kanji_ids": [
      "0587",
      "0588",
      "1688",
      "1820"
    ],
    "id": "grade2:medium:L136:ea37c0fa1a"
  }
]